<frame>
  <template xmlns:xsi="http://www.w3.org/2001/XMLSchema-instance" 
    xsi:noNamespaceSchemaLocation="frame_schema.xsd" 
    name="FCGPN_ID_ACCEPT" 
    showName="FC GPN_ID Accept"
    version="1.0"
    category="Fibre Channel"
    readonly="true"
    validate="true"
    firstPdu="fcgs:GpnIdAccept"
    description="FC GPN_ID Accept">
    <pdus>
      <pdu name="gpnIdAccept1" pdu="fcgs:GpnIdAccept" >
        <ctIuPreamble>
          <commandRespondCode>8002</commandRespondCode>
        </ctIuPreamble>
      </pdu>
    </pdus>    
  </template>
</frame>