<?xml version="1.0" encoding="utf-8"?>
<frame>
   <template xmlns:xsi="http://www.w3.org/2001/XMLSchema-instance" xsi:noNamespaceSchemaLocation="frame_schema.xsd" name="IPv4DestTCPDestPort" showName="IPv4 Dest TCP Dest Port" version="1.0" category="Favorites" readonly="false" validate="true" firstPdu="ethernet:EthernetII" description="IPv4 Destination Address and TCP Destination Port">
      <pdus>
<pdu name="proto1" pdu="ethernet:EthernetII">
</pdu>
<pdu name="IPv4_1" pdu="ipv4:IPv4">
<destAddr filterMinValue="000.000.000.000" filterMaxValue="255.255.255.255">255.255.255.255</destAddr>
<protocol  filterMinValue="6" filterMaxValue="6">6</protocol>
</pdu>
<pdu name="Tcp_1" pdu="tcp:Tcp">
<destPort filterMinValue="0" filterMaxValue="65535">65535</destPort>
</pdu>
</pdus>
</template>
</frame>